[
    {
        "value": "Issue with my Bet",
        "display": "Issue with my Bet"
    },
    {
        "value": "Payments",
        "display": "Payments"
    },
    {
        "value": "Account Access Issues",
        "display": "Account Access Issues"
    },
    {
        "value": "Safer Gambling",
        "display": "Safer Gambling"
    },
    {
        "value": "Build a Bet",
        "display": "Build a Bet"
    },
    {
        "value": "Speak with an Agent",
        "display": "Speak with an Agent"
    }

]